filtpostqc_eu/__init__.py
filtpostqc_eu/cli.py
filtpostqc_eu-0.1.1.dist-info/METADATA
filtpostqc_eu-0.1.1.dist-info/WHEEL
filtpostqc_eu-0.1.1.dist-info/entry_points.txt
filtpostqc_eu-0.1.1.dist-info/top_level.txt
filtpostqc_eu-0.1.1.dist-info/RECORD
