Metadata-Version: 2.4
Name: FiltpostQC-EU
Version: 0.1.1
Summary: A CLI tool to apply post-GWAS QC filtering to Regenie merged summary statistics using EU-based variant filters.
Home-page: https://github.com/EtienneNtumba/FiltpostQC-EU
Author: Etienne Kabongo
Author-email: etienne@example.com
License: MIT
Classifier: Programming Language :: Python :: 3
Classifier: Programming Language :: Python :: 3.7
Classifier: License :: OSI Approved :: MIT License
Classifier: Operating System :: OS Independent
Classifier: Intended Audience :: Science/Research
Classifier: Topic :: Scientific/Engineering :: Bio-Informatics
Requires-Python: >=3.7
Requires-Dist: pandas>=1.0
Dynamic: author
Dynamic: author-email
Dynamic: classifier
Dynamic: description
Dynamic: description-content-type
Dynamic: home-page
Dynamic: license
Dynamic: requires-dist
Dynamic: requires-python
Dynamic: summary
